{
	"name": "lightningOrb_shadow",
	"plugin-id": "Sprite",
	"sid": 797180433478193,
	"isGlobal": false,
	"instanceVariables": [],
	"behaviorTypes": [],
	"effectTypes": [],
	"animations": {
		"items": [
			{
				"frames": [
					{
						"width": 34,
						"height": 23,
						"originX": 3.1470588235294117,
						"originY": 2.3043478260869565,
						"originalSource": "",
						"exportFormat": "lossless",
						"exportQuality": 0.8,
						"fileType": "image/png",
						"imageSpriteId": 6084050,
						"useCollisionPoly": true,
						"duration": 1,
						"tag": ""
					},
					{
						"width": 35,
						"height": 22,
						"originX": 3.1142857142857143,
						"originY": 2.590909090909091,
						"originalSource": "",
						"exportFormat": "lossless",
						"exportQuality": 0.8,
						"fileType": "image/png",
						"imageSpriteId": 2066611,
						"useCollisionPoly": true,
						"duration": 1,
						"tag": ""
					},
					{
						"width": 34,
						"height": 16,
						"originX": 3.176470588235294,
						"originY": 3.1875,
						"originalSource": "",
						"exportFormat": "lossless",
						"exportQuality": 0.8,
						"fileType": "image/png",
						"imageSpriteId": 4064802,
						"useCollisionPoly": true,
						"duration": 1,
						"tag": ""
					},
					{
						"width": 38,
						"height": 22,
						"originX": 2.973684210526316,
						"originY": 2.4545454545454546,
						"originalSource": "",
						"exportFormat": "lossless",
						"exportQuality": 0.8,
						"fileType": "image/png",
						"imageSpriteId": 1262467,
						"useCollisionPoly": true,
						"duration": 1,
						"tag": ""
					},
					{
						"width": 34,
						"height": 20,
						"originX": 3.088235294117647,
						"originY": 2.6,
						"originalSource": "",
						"exportFormat": "lossless",
						"exportQuality": 0.8,
						"fileType": "image/png",
						"imageSpriteId": 4059795,
						"useCollisionPoly": true,
						"duration": 1,
						"tag": ""
					},
					{
						"width": 32,
						"height": 24,
						"originX": 3.3125,
						"originY": 2.375,
						"originalSource": "",
						"exportFormat": "lossless",
						"exportQuality": 0.8,
						"fileType": "image/png",
						"imageSpriteId": 6896965,
						"useCollisionPoly": true,
						"duration": 1,
						"tag": ""
					},
					{
						"width": 34,
						"height": 22,
						"originX": 3.235294117647059,
						"originY": 2.5,
						"originalSource": "",
						"exportFormat": "lossless",
						"exportQuality": 0.8,
						"fileType": "image/png",
						"imageSpriteId": 5253606,
						"useCollisionPoly": true,
						"duration": 1,
						"tag": ""
					},
					{
						"width": 36,
						"height": 18,
						"originX": 2.888888888888889,
						"originY": 2.9444444444444446,
						"originalSource": "",
						"exportFormat": "lossless",
						"exportQuality": 0.8,
						"fileType": "image/png",
						"imageSpriteId": 646829,
						"useCollisionPoly": true,
						"duration": 1,
						"tag": ""
					},
					{
						"width": 42,
						"height": 24,
						"originX": 2.642857142857143,
						"originY": 2.375,
						"originalSource": "",
						"exportFormat": "lossless",
						"exportQuality": 0.8,
						"fileType": "image/png",
						"imageSpriteId": 4728577,
						"useCollisionPoly": true,
						"duration": 1,
						"tag": ""
					},
					{
						"width": 43,
						"height": 20,
						"originX": 2.697674418604651,
						"originY": 2.65,
						"originalSource": "",
						"exportFormat": "lossless",
						"exportQuality": 0.8,
						"fileType": "image/png",
						"imageSpriteId": 4447738,
						"useCollisionPoly": true,
						"duration": 1,
						"tag": ""
					}
				],
				"sid": 645898759268774,
				"name": "Animation 1",
				"isLooping": false,
				"isPingPong": false,
				"repeatCount": 1,
				"repeatTo": 0,
				"speed": 30
			}
		],
		"subfolders": []
	}
}